enocean_ble-0.1.4.dist-info/METADATA
enocean_ble-0.1.4.dist-info/WHEEL
enocean_ble-0.1.4.dist-info/licenses/LICENSE
enocean_ble/__init__.py
enocean_ble/__main__.py
enocean_ble/decoder.py
enocean_ble/parser.py
enocean_ble-0.1.4.dist-info/RECORD
