Metadata-Version: 2.1
Name: enocean-ble
Version: 0.1.4
Author-Email: Christian Ohde <christian.s1989@gmail.com>
License: MIT
Requires-Python: >=3.10
Requires-Dist: bleak>=0.20.2
Requires-Dist: typer>=0.9.0
Requires-Dist: bluetooth-sensor-state-data>=1.6.1
Requires-Dist: bluetooth-data-tools>=1.2.0
Requires-Dist: home-assistant-bluetooth>=1.10.0
Requires-Dist: sensor-state-data>=2.16.0
Requires-Dist: pycryptodome>=3.18.0
